{
  "world": {
    "workingBounds": { "x": 0, "y": 0, "width": 800, "height": 600 },
    "simulationBounds": { "x": 0, "y": 0, "width": 800, "height": 1000 },
    "wallThickness": 60,
    "gravity": { "x": 0, "y": -1 }
  },
  "objects": [
    {
      "id": "zone_box_1",
      "type": "box",
      "x": 400,
      "y": 200,
      "width": 100,
      "height": 100,
      "depth": 100,
      "isStatic": true,
      "isSensor": true,
      "isFixed": true,
      "color": { "r": 0.2, "g": 0.8, "b": 0.2, "a": 0.3 }
    }
  ],
  "inventory": [
    {
      "id": "inv_sphere_small",
      "displayName": "Small Sphere",
      "count": 5,
      "objectProperties": {
        "type": "circle",
        "radius": 15,
        "mass": 0.5,
        "restitution": 0.8,
        "friction": 0.02,
        "color": { "r": 0.5, "g": 0.5, "b": 1.0 },
        "configLimits": {
          "mass": { "min": 0.1, "max": 2.0 },
          "friction": { "min": 0.0, "max": 0.1 },
          "restitution": { "min": 0.5, "max": 1.0 }
        }
      }
    },
    {
      "id": "inv_box_small",
      "displayName": "Small Box",
      "count": 5,
      "objectProperties": {
        "type": "box",
        "width": 50,
        "height": 50,
        "depth": 50,
        "mass": 1,
        "restitution": 0.4,
        "friction": 0.05,
        "color": { "r": 0.5, "g": 1.0, "b": 0.5 },
        "configLimits": {
          "mass": { "min": 0.5, "max": 5.0 },
          "friction": { "min": 0.01, "max": 0.8 },
          "restitution": { "min": 0.0, "max": 0.6 }
        }
      }
    },
    {
      "id": "inv_long_small",
      "displayName": "long Box",
      "count": 5,
      "objectProperties": {
        "type": "box",
        "width": 300,
        "height": 10,
        "depth": 50,
        "mass": 1,
        "restitution": 0.4,
        "friction": 0.05,
        "color": { "r": 0.5, "g": 1.0, "b": 0.5 },
        "configLimits": {
          "mass": { "min": 0.2, "max": 3.0 },
          "friction": { "min": 0.1, "max": 0.9 },
          "restitution": { "min": 0.1, "max": 0.5 }
        }
      }
    }
  ],
  "objectives": [
    {
      "id": "obj_max_height_sphere",
      "type": "maxHeight",
      "targetId": "inv_sphere_small",
      "displayName": "Max Height Sphere"
    },
    {
      "id": "obj_box_in_zone",
      "type": "stayInZone",
      "targetId": "inv_sphere_small",
      "zone": { "x": 350, "y": 150, "width": 100, "height": 100 },
      "duration": 3,
      "displayName": "Keep Box in Zone (3s)"
    }
  ]
}
